{
  "PluginDescriptions": [
    {
      "Name": "HealthBars",
      "OriginalAuthor": "OriathHub",
      "Forks": [
        {
          "Author": "danthespal",
          "Location": "danthespal",
          "Name": "HealthBars",
          "LatestCommit": {
            "Message": "Merge branch \u0027main\u0027 of https://github.com/danthespal/HealthBars",
            "Hash": "bb214eaccbf3225d8560f7312ceb0aa1d691343c",
            "Author": "danthespal",
            "Date": "2026-06-27T09:34:32Z"
          },
          "Releases": []
        }
      ],
      "Description": "Draw health, energy shield, mana and ward bars above entities in the game world. Supports customisable bar style and per-monster-type visibility rules.",
      "EndorsedAuthor": "danthespal"
    },
    {
      "Name": "Radar",
      "OriginalAuthor": "OriathHub",
      "Forks": [
        {
          "Author": "danthespal",
          "Location": "danthespal",
          "Name": "Radar",
          "LatestCommit": {
            "Message": "update sdk",
            "Hash": "3398b4aa21afd46ec7bfd951823dd8bc413d455e",
            "Author": "danthespal",
            "Date": "2026-06-27T09:35:04Z"
          },
          "Releases": []
        }
      ],
      "Description": "Draws a live minimap overlay with entity positions, POI markers, and pathfinding routes. Highlights stairs, boss arenas, and Delve chests using built-in TGT file lists.",
      "EndorsedAuthor": "danthespal"
    },
    {
      "Name": "NinjaPricer",
      "OriginalAuthor": "OriathHub",
      "Forks": [
        {
          "Author": "danthespal",
          "Location": "danthespal",
          "Name": "NinjaPricer",
          "LatestCommit": {
            "Message": "Merge branch \u0027main\u0027 of https://github.com/danthespal/NinjaPricer",
            "Hash": "364751c9ce7b2286f85ced4f6d7ef2ccb269a444",
            "Author": "danthespal",
            "Date": "2026-06-27T09:34:47Z"
          },
          "Releases": []
        }
      ],
      "Description": "Overlays poe.ninja price tags on stash cells and lists all items in open tabs in a sidebar window. Highlights valuable items above a configurable chaos threshold.",
      "EndorsedAuthor": "danthespal"
    },
    {
      "Name": "AutoHotKeyTrigger",
      "OriginalAuthor": "OriathHub",
      "Forks": [
        {
          "Author": "danthespal",
          "Location": "danthespal",
          "Name": "AutoHotKeyTrigger",
          "LatestCommit": {
            "Message": "Merge branch \u0027main\u0027 of https://github.com/danthespal/AutoHotKeyTrigger",
            "Hash": "bd5c910e44c9ae9a880631fe9281e36a31066e52",
            "Author": "danthespal",
            "Date": "2026-06-27T09:34:17Z"
          },
          "Releases": []
        }
      ],
      "Description": "Automatically presses keys for flasks and skills when user-defined conditions are met (vitals, buffs, nearby monsters, status effects). Supports multiple profiles and an emergency AutoQuit trigger.",
      "EndorsedAuthor": "danthespal"
    },
    {
      "Name": "Atlas",
      "OriginalAuthor": "OriathHub",
      "Forks": [
        {
          "Author": "danthespal",
          "Location": "danthespal",
          "Name": "Atlas",
          "LatestCommit": {
            "Message": "update sdk",
            "Hash": "dae212058f33b1ee01f7f8db759fd7888293a3fa",
            "Author": "danthespal",
            "Date": "2026-06-27T09:34:06Z"
          },
          "Releases": []
        }
      ],
      "Description": "Draws labels, biome borders, and group colours on the endgame atlas map. Supports named map groups, content filtering, and map search.",
      "EndorsedAuthor": "danthespal"
    }
  ],
  "Updated": "2026-06-27T15:03:41.0357988Z",
  "ModelVersion": "1"
}